{
    "actionModel": "MAPF",
    "teamSize": 5000,
    "numTaskFinished": 1747,
    "makespan": 140,
    "numPlannerErrors": 0,
    "numScheduleErrors": 0,
    "numEntryTimeouts": 0,
    "schedulerHierarchyBuildTime": 2.278781069,
    "schedulerHierarchyLevelNodeCounts": [
        978096,
        26384,
        7661
    ],
    "timeStepMetrics": [
        {
            "SchedulerSolveTime": 0.068515248,
            "SchedulerGuidePathTime": 0.0,
            "PlannerTime": 0.884764319
        },
        {
            "SchedulerSolveTime": 0.039266795,
            "SchedulerGuidePathTime": 0.0,
            "PlannerTime": 0.900249709
        },
        {
            "SchedulerSolveTime": 0.057962833,
            "SchedulerGuidePathTime": 0.0,
            "PlannerTime": 0.946250487
        },
        {
            "SchedulerSolveTime": 0.044654466,
            "SchedulerGuidePathTime": 0.0,
            "PlannerTime": 0.972266357
        },
        {
            "SchedulerSolveTime": 0.043348674,
            "SchedulerGuidePathTime": 0.0,
            "PlannerTime": 1.004917511
        },
        {
            "SchedulerSolveTime": 0.043348674,
            "SchedulerGuidePathTime": 0.0,
            "PlannerTime": 1.004917511
        },
        {
            "SchedulerSolveTime": 0.028542347,
            "SchedulerGuidePathTime": 0.0,
            "PlannerTime": 1.046436628
        },
        {
            "SchedulerSolveTime": 0.028542347,
            "SchedulerGuidePathTime": 0.0,
            "PlannerTime": 1.046436628
        },
        {
            "SchedulerSolveTime": 0.024218863,
            "SchedulerGuidePathTime": 0.0,
            "PlannerTime": 1.054216683
        },
        {
            "SchedulerSolveTime": 0.024218863,
            "SchedulerGuidePathTime": 0.0,
            "PlannerTime": 1.054216683
        },
        {
            "SchedulerSolveTime": 0.039304765,
            "SchedulerGuidePathTime": 0.0,
            "PlannerTime": 1.0594235
        },
        {
            "SchedulerSolveTime": 0.039304765,
            "SchedulerGuidePathTime": 0.0,
            "PlannerTime": 1.0594235
        },
        {
            "SchedulerSolveTime": 0.027324089,
            "SchedulerGuidePathTime": 0.0,
            "PlannerTime": 1.10000694
        },
        {
            "SchedulerSolveTime": 0.027324089,
            "SchedulerGuidePathTime": 0.0,
            "PlannerTime": 1.10000694
        },
        {
            "SchedulerSolveTime": 0.02589607,
            "SchedulerGuidePathTime": 0.0,
            "PlannerTime": 1.110754413
        },
        {
            "SchedulerSolveTime": 0.02589607,
            "SchedulerGuidePathTime": 0.0,
            "PlannerTime": 1.110754413
        },
        {
            "SchedulerSolveTime": 0.049014516,
            "SchedulerGuidePathTime": 0.0,
            "PlannerTime": 1.149835031
        },
        {
            "SchedulerSolveTime": 0.049014516,
            "SchedulerGuidePathTime": 0.0,
            "PlannerTime": 1.149835031
        },
        {
            "SchedulerSolveTime": 0.046584186,
            "SchedulerGuidePathTime": 0.0,
            "PlannerTime": 1.119160918
        },
        {
            "SchedulerSolveTime": 0.046584186,
            "SchedulerGuidePathTime": 0.0,
            "PlannerTime": 1.119160918
        },
        {
            "SchedulerSolveTime": 0.040468929,
            "SchedulerGuidePathTime": 0.0,
            "PlannerTime": 1.131312278
        },
        {
            "SchedulerSolveTime": 0.040468929,
            "SchedulerGuidePathTime": 0.0,
            "PlannerTime": 1.131312278
        },
        {
            "SchedulerSolveTime": 0.047765783,
            "SchedulerGuidePathTime": 0.0,
            "PlannerTime": 1.120586864
        },
        {
            "SchedulerSolveTime": 0.047765783,
            "SchedulerGuidePathTime": 0.0,
            "PlannerTime": 1.120586864
        },
        {
            "SchedulerSolveTime": 0.045365849,
            "SchedulerGuidePathTime": 0.0,
            "PlannerTime": 1.13936056
        },
        {
            "SchedulerSolveTime": 0.045365849,
            "SchedulerGuidePathTime": 0.0,
            "PlannerTime": 1.13936056
        },
        {
            "SchedulerSolveTime": 0.041808231,
            "SchedulerGuidePathTime": 0.0,
            "PlannerTime": 1.122845451
        },
        {
            "SchedulerSolveTime": 0.041808231,
            "SchedulerGuidePathTime": 0.0,
            "PlannerTime": 1.122845451
        },
        {
            "SchedulerSolveTime": 0.031406751,
            "SchedulerGuidePathTime": 0.0,
            "PlannerTime": 1.145613271
        },
        {
            "SchedulerSolveTime": 0.031406751,
            "SchedulerGuidePathTime": 0.0,
            "PlannerTime": 1.145613271
        },
        {
            "SchedulerSolveTime": 0.048055285,
            "SchedulerGuidePathTime": 0.0,
            "PlannerTime": 1.150212126
        },
        {
            "SchedulerSolveTime": 0.048055285,
            "SchedulerGuidePathTime": 0.0,
            "PlannerTime": 1.150212126
        },
        {
            "SchedulerSolveTime": 0.035755601,
            "SchedulerGuidePathTime": 0.0,
            "PlannerTime": 1.138071146
        },
        {
            "SchedulerSolveTime": 0.035755601,
            "SchedulerGuidePathTime": 0.0,
            "PlannerTime": 1.138071146
        },
        {
            "SchedulerSolveTime": 0.044922936,
            "SchedulerGuidePathTime": 0.0,
            "PlannerTime": 1.14031956
        },
        {
            "SchedulerSolveTime": 0.044922936,
            "SchedulerGuidePathTime": 0.0,
            "PlannerTime": 1.14031956
        },
        {
            "SchedulerSolveTime": 0.039264195,
            "SchedulerGuidePathTime": 0.0,
            "PlannerTime": 1.146381149
        },
        {
            "SchedulerSolveTime": 0.039264195,
            "SchedulerGuidePathTime": 0.0,
            "PlannerTime": 1.146381149
        },
        {
            "SchedulerSolveTime": 0.044545356,
            "SchedulerGuidePathTime": 0.0,
            "PlannerTime": 1.145644732
        },
        {
            "SchedulerSolveTime": 0.044545356,
            "SchedulerGuidePathTime": 0.0,
            "PlannerTime": 1.145644732
        },
        {
            "SchedulerSolveTime": 0.055659474,
            "SchedulerGuidePathTime": 0.0,
            "PlannerTime": 1.146022624
        },
        {
            "SchedulerSolveTime": 0.055659474,
            "SchedulerGuidePathTime": 0.0,
            "PlannerTime": 1.146022624
        },
        {
            "SchedulerSolveTime": 0.02994128,
            "SchedulerGuidePathTime": 0.0,
            "PlannerTime": 1.136455674
        },
        {
            "SchedulerSolveTime": 0.02994128,
            "SchedulerGuidePathTime": 0.0,
            "PlannerTime": 1.136455674
        },
        {
            "SchedulerSolveTime": 0.039150533,
            "SchedulerGuidePathTime": 0.0,
            "PlannerTime": 1.154971538
        },
        {
            "SchedulerSolveTime": 0.039150533,
            "SchedulerGuidePathTime": 0.0,
            "PlannerTime": 1.154971538
        },
        {
            "SchedulerSolveTime": 0.041872971,
            "SchedulerGuidePathTime": 0.0,
            "PlannerTime": 1.16330518
        },
        {
            "SchedulerSolveTime": 0.041872971,
            "SchedulerGuidePathTime": 0.0,
            "PlannerTime": 1.16330518
        },
        {
            "SchedulerSolveTime": 0.034648843,
            "SchedulerGuidePathTime": 0.0,
            "PlannerTime": 1.195886768
        },
        {
            "SchedulerSolveTime": 0.034648843,
            "SchedulerGuidePathTime": 0.0,
            "PlannerTime": 1.195886768
        },
        {
            "SchedulerSolveTime": 0.027281787,
            "SchedulerGuidePathTime": 0.0,
            "PlannerTime": 1.175175504
        },
        {
            "SchedulerSolveTime": 0.027281787,
            "SchedulerGuidePathTime": 0.0,
            "PlannerTime": 1.175175504
        },
        {
            "SchedulerSolveTime": 0.040423169,
            "SchedulerGuidePathTime": 0.0,
            "PlannerTime": 1.168820531
        },
        {
            "SchedulerSolveTime": 0.040423169,
            "SchedulerGuidePathTime": 0.0,
            "PlannerTime": 1.168820531
        },
        {
            "SchedulerSolveTime": 0.053057649,
            "SchedulerGuidePathTime": 0.0,
            "PlannerTime": 1.178518054
        },
        {
            "SchedulerSolveTime": 0.053057649,
            "SchedulerGuidePathTime": 0.0,
            "PlannerTime": 1.178518054
        },
        {
            "SchedulerSolveTime": 0.03598026,
            "SchedulerGuidePathTime": 0.0,
            "PlannerTime": 1.172168012
        },
        {
            "SchedulerSolveTime": 0.03598026,
            "SchedulerGuidePathTime": 0.0,
            "PlannerTime": 1.172168012
        },
        {
            "SchedulerSolveTime": 0.027842499,
            "SchedulerGuidePathTime": 0.0,
            "PlannerTime": 1.162033018
        },
        {
            "SchedulerSolveTime": 0.027842499,
            "SchedulerGuidePathTime": 0.0,
            "PlannerTime": 1.162033018
        },
        {
            "SchedulerSolveTime": 0.037839821,
            "SchedulerGuidePathTime": 0.0,
            "PlannerTime": 1.159465131
        },
        {
            "SchedulerSolveTime": 0.037839821,
            "SchedulerGuidePathTime": 0.0,
            "PlannerTime": 1.159465131
        },
        {
            "SchedulerSolveTime": 0.025948244,
            "SchedulerGuidePathTime": 0.0,
            "PlannerTime": 1.146164246
        },
        {
            "SchedulerSolveTime": 0.025948244,
            "SchedulerGuidePathTime": 0.0,
            "PlannerTime": 1.146164246
        },
        {
            "SchedulerSolveTime": 0.014785276,
            "SchedulerGuidePathTime": 0.0,
            "PlannerTime": 1.156174786
        },
        {
            "SchedulerSolveTime": 0.014785276,
            "SchedulerGuidePathTime": 0.0,
            "PlannerTime": 1.156174786
        },
        {
            "SchedulerSolveTime": 0.030119031,
            "SchedulerGuidePathTime": 0.0,
            "PlannerTime": 1.183361978
        },
        {
            "SchedulerSolveTime": 0.030119031,
            "SchedulerGuidePathTime": 0.0,
            "PlannerTime": 1.183361978
        },
        {
            "SchedulerSolveTime": 0.035733497,
            "SchedulerGuidePathTime": 0.0,
            "PlannerTime": 1.169927973
        },
        {
            "SchedulerSolveTime": 0.035733497,
            "SchedulerGuidePathTime": 0.0,
            "PlannerTime": 1.169927973
        },
        {
            "SchedulerSolveTime": 0.039411038,
            "SchedulerGuidePathTime": 0.0,
            "PlannerTime": 1.202662355
        },
        {
            "SchedulerSolveTime": 0.039411038,
            "SchedulerGuidePathTime": 0.0,
            "PlannerTime": 1.202662355
        },
        {
            "SchedulerSolveTime": 0.04403243,
            "SchedulerGuidePathTime": 0.0,
            "PlannerTime": 1.189470804
        },
        {
            "SchedulerSolveTime": 0.04403243,
            "SchedulerGuidePathTime": 0.0,
            "PlannerTime": 1.189470804
        },
        {
            "SchedulerSolveTime": 0.051106887,
            "SchedulerGuidePathTime": 0.0,
            "PlannerTime": 1.185858729
        },
        {
            "SchedulerSolveTime": 0.051106887,
            "SchedulerGuidePathTime": 0.0,
            "PlannerTime": 1.185858729
        },
        {
            "SchedulerSolveTime": 0.028882589,
            "SchedulerGuidePathTime": 0.0,
            "PlannerTime": 1.17852919
        },
        {
            "SchedulerSolveTime": 0.028882589,
            "SchedulerGuidePathTime": 0.0,
            "PlannerTime": 1.17852919
        },
        {
            "SchedulerSolveTime": 0.031409832,
            "SchedulerGuidePathTime": 0.0,
            "PlannerTime": 1.182686385
        },
        {
            "SchedulerSolveTime": 0.031409832,
            "SchedulerGuidePathTime": 0.0,
            "PlannerTime": 1.182686385
        },
        {
            "SchedulerSolveTime": 0.020834407,
            "SchedulerGuidePathTime": 0.0,
            "PlannerTime": 1.193942331
        },
        {
            "SchedulerSolveTime": 0.020834407,
            "SchedulerGuidePathTime": 0.0,
            "PlannerTime": 1.193942331
        },
        {
            "SchedulerSolveTime": 0.037337015,
            "SchedulerGuidePathTime": 0.0,
            "PlannerTime": 1.094925495
        },
        {
            "SchedulerSolveTime": 0.037337015,
            "SchedulerGuidePathTime": 0.0,
            "PlannerTime": 1.094925495
        },
        {
            "SchedulerSolveTime": 0.026963309,
            "SchedulerGuidePathTime": 0.0,
            "PlannerTime": 1.14231088
        },
        {
            "SchedulerSolveTime": 0.026963309,
            "SchedulerGuidePathTime": 0.0,
            "PlannerTime": 1.14231088
        },
        {
            "SchedulerSolveTime": 0.058252193,
            "SchedulerGuidePathTime": 0.0,
            "PlannerTime": 1.157510598
        },
        {
            "SchedulerSolveTime": 0.058252193,
            "SchedulerGuidePathTime": 0.0,
            "PlannerTime": 1.157510598
        },
        {
            "SchedulerSolveTime": 0.045625789,
            "SchedulerGuidePathTime": 0.0,
            "PlannerTime": 1.211484506
        },
        {
            "SchedulerSolveTime": 0.045625789,
            "SchedulerGuidePathTime": 0.0,
            "PlannerTime": 1.211484506
        },
        {
            "SchedulerSolveTime": 0.026414978,
            "SchedulerGuidePathTime": 0.0,
            "PlannerTime": 1.142546857
        },
        {
            "SchedulerSolveTime": 0.026414978,
            "SchedulerGuidePathTime": 0.0,
            "PlannerTime": 1.142546857
        },
        {
            "SchedulerSolveTime": 0.051427255,
            "SchedulerGuidePathTime": 0.0,
            "PlannerTime": 1.202686765
        },
        {
            "SchedulerSolveTime": 0.051427255,
            "SchedulerGuidePathTime": 0.0,
            "PlannerTime": 1.202686765
        },
        {
            "SchedulerSolveTime": 0.016611152,
            "SchedulerGuidePathTime": 0.0,
            "PlannerTime": 1.077836424
        },
        {
            "SchedulerSolveTime": 0.016611152,
            "SchedulerGuidePathTime": 0.0,
            "PlannerTime": 1.077836424
        },
        {
            "SchedulerSolveTime": 0.025218585,
            "SchedulerGuidePathTime": 0.0,
            "PlannerTime": 1.088093326
        },
        {
            "SchedulerSolveTime": 0.025218585,
            "SchedulerGuidePathTime": 0.0,
            "PlannerTime": 1.088093326
        },
        {
            "SchedulerSolveTime": 0.02474255,
            "SchedulerGuidePathTime": 0.0,
            "PlannerTime": 1.124948451
        },
        {
            "SchedulerSolveTime": 0.02474255,
            "SchedulerGuidePathTime": 0.0,
            "PlannerTime": 1.124948451
        },
        {
            "SchedulerSolveTime": 0.039855078,
            "SchedulerGuidePathTime": 0.0,
            "PlannerTime": 1.116416365
        },
        {
            "SchedulerSolveTime": 0.039855078,
            "SchedulerGuidePathTime": 0.0,
            "PlannerTime": 1.116416365
        },
        {
            "SchedulerSolveTime": 0.037111068999999997,
            "SchedulerGuidePathTime": 0.0,
            "PlannerTime": 1.197854058
        },
        {
            "SchedulerSolveTime": 0.037111068999999997,
            "SchedulerGuidePathTime": 0.0,
            "PlannerTime": 1.197854058
        },
        {
            "SchedulerSolveTime": 0.041622333,
            "SchedulerGuidePathTime": 0.0,
            "PlannerTime": 1.09787423
        },
        {
            "SchedulerSolveTime": 0.041622333,
            "SchedulerGuidePathTime": 0.0,
            "PlannerTime": 1.09787423
        },
        {
            "SchedulerSolveTime": 0.01938707,
            "SchedulerGuidePathTime": 0.0,
            "PlannerTime": 1.21181308
        },
        {
            "SchedulerSolveTime": 0.01938707,
            "SchedulerGuidePathTime": 0.0,
            "PlannerTime": 1.21181308
        },
        {
            "SchedulerSolveTime": 0.026780644,
            "SchedulerGuidePathTime": 0.0,
            "PlannerTime": 1.11671314
        },
        {
            "SchedulerSolveTime": 0.026780644,
            "SchedulerGuidePathTime": 0.0,
            "PlannerTime": 1.11671314
        },
        {
            "SchedulerSolveTime": 0.06378914,
            "SchedulerGuidePathTime": 0.0,
            "PlannerTime": 1.188626579
        },
        {
            "SchedulerSolveTime": 0.06378914,
            "SchedulerGuidePathTime": 0.0,
            "PlannerTime": 1.188626579
        },
        {
            "SchedulerSolveTime": 0.057461514,
            "SchedulerGuidePathTime": 0.0,
            "PlannerTime": 1.106541133
        },
        {
            "SchedulerSolveTime": 0.057461514,
            "SchedulerGuidePathTime": 0.0,
            "PlannerTime": 1.106541133
        },
        {
            "SchedulerSolveTime": 0.043301535,
            "SchedulerGuidePathTime": 0.0,
            "PlannerTime": 1.206235781
        },
        {
            "SchedulerSolveTime": 0.043301535,
            "SchedulerGuidePathTime": 0.0,
            "PlannerTime": 1.206235781
        },
        {
            "SchedulerSolveTime": 0.042222209,
            "SchedulerGuidePathTime": 0.0,
            "PlannerTime": 1.11048922
        },
        {
            "SchedulerSolveTime": 0.042222209,
            "SchedulerGuidePathTime": 0.0,
            "PlannerTime": 1.11048922
        },
        {
            "SchedulerSolveTime": 0.012682668,
            "SchedulerGuidePathTime": 0.0,
            "PlannerTime": 1.134267884
        },
        {
            "SchedulerSolveTime": 0.012682668,
            "SchedulerGuidePathTime": 0.0,
            "PlannerTime": 1.134267884
        },
        {
            "SchedulerSolveTime": 0.038645908,
            "SchedulerGuidePathTime": 0.0,
            "PlannerTime": 1.108486191
        },
        {
            "SchedulerSolveTime": 0.038645908,
            "SchedulerGuidePathTime": 0.0,
            "PlannerTime": 1.108486191
        },
        {
            "SchedulerSolveTime": 0.03870076,
            "SchedulerGuidePathTime": 0.0,
            "PlannerTime": 1.111306127
        },
        {
            "SchedulerSolveTime": 0.03870076,
            "SchedulerGuidePathTime": 0.0,
            "PlannerTime": 1.111306127
        },
        {
            "SchedulerSolveTime": 0.020398186,
            "SchedulerGuidePathTime": 0.0,
            "PlannerTime": 1.107478901
        },
        {
            "SchedulerSolveTime": 0.020398186,
            "SchedulerGuidePathTime": 0.0,
            "PlannerTime": 1.107478901
        },
        {
            "SchedulerSolveTime": 0.02508462,
            "SchedulerGuidePathTime": 0.0,
            "PlannerTime": 1.111320705
        },
        {
            "SchedulerSolveTime": 0.02508462,
            "SchedulerGuidePathTime": 0.0,
            "PlannerTime": 1.111320705
        },
        {
            "SchedulerSolveTime": 0.033727278,
            "SchedulerGuidePathTime": 0.0,
            "PlannerTime": 1.109353347
        },
        {
            "SchedulerSolveTime": 0.033727278,
            "SchedulerGuidePathTime": 0.0,
            "PlannerTime": 1.109353347
        },
        {
            "SchedulerSolveTime": 0.042337112,
            "SchedulerGuidePathTime": 0.0,
            "PlannerTime": 1.095651522
        },
        {
            "SchedulerSolveTime": 0.042337112,
            "SchedulerGuidePathTime": 0.0,
            "PlannerTime": 1.095651522
        },
        {
            "SchedulerSolveTime": 0.031023203,
            "SchedulerGuidePathTime": 0.0,
            "PlannerTime": 1.106658713
        },
        {
            "SchedulerSolveTime": 0.031023203,
            "SchedulerGuidePathTime": 0.0,
            "PlannerTime": 1.106658713
        },
        {
            "SchedulerSolveTime": 0.01104719,
            "SchedulerGuidePathTime": 0.0,
            "PlannerTime": 1.092158267
        },
        {
            "SchedulerSolveTime": 0.01104719,
            "SchedulerGuidePathTime": 0.0,
            "PlannerTime": 1.092158267
        },
        {
            "SchedulerSolveTime": 0.052458243,
            "SchedulerGuidePathTime": 0.0,
            "PlannerTime": 1.100754303
        },
        {
            "SchedulerSolveTime": 0.052458243,
            "SchedulerGuidePathTime": 0.0,
            "PlannerTime": 1.100754303
        },
        {
            "SchedulerSolveTime": 0.028139752,
            "SchedulerGuidePathTime": 0.0,
            "PlannerTime": 1.130019121
        },
        {
            "SchedulerSolveTime": 0.028139752,
            "SchedulerGuidePathTime": 0.0,
            "PlannerTime": 1.130019121
        }
    ]
}